iotile/__init__.py
iotile/sg/__init__.py
iotile/sg/compiler.py
iotile/sg/exceptions.py
iotile/sg/graph.py
iotile/sg/known_constants.py
iotile/sg/model.py
iotile/sg/node.py
iotile/sg/node_descriptor.py
iotile/sg/processors.py
iotile/sg/sensor_log.py
iotile/sg/slot.py
iotile/sg/stream.py
iotile/sg/streamer.py
iotile/sg/streamer_descriptor.py
iotile/sg/walker.py
iotile/sg/engine/__init__.py
iotile/sg/engine/in_memory.py
iotile/sg/optimizer/__init__.py
iotile/sg/optimizer/optimizer.py
iotile/sg/optimizer/passes/__init__.py
iotile/sg/optimizer/passes/convert_to_always.py
iotile/sg/optimizer/passes/dead_code_elimination.py
iotile/sg/optimizer/passes/downgrade_copyall.py
iotile/sg/optimizer/passes/remove_constants.py
iotile/sg/optimizer/passes/remove_copylatest.py
iotile/sg/output_formats/__init__.py
iotile/sg/output_formats/ascii.py
iotile/sg/output_formats/config.py
iotile/sg/output_formats/script.py
iotile/sg/output_formats/snippet.py
iotile/sg/parser/__init__.py
iotile/sg/parser/language.py
iotile/sg/parser/parser_v1.py
iotile/sg/parser/stream_allocator.py
iotile/sg/parser/scopes/__init__.py
iotile/sg/parser/scopes/gated_clock_scope.py
iotile/sg/parser/scopes/root_scope.py
iotile/sg/parser/scopes/scope.py
iotile/sg/parser/scopes/trigger_scope.py
iotile/sg/parser/statements/__init__.py
iotile/sg/parser/statements/call_statement.py
iotile/sg/parser/statements/config_block.py
iotile/sg/parser/statements/config_statement.py
iotile/sg/parser/statements/copy_statement.py
iotile/sg/parser/statements/every_block.py
iotile/sg/parser/statements/latch_block.py
iotile/sg/parser/statements/meta_statement.py
iotile/sg/parser/statements/on_block.py
iotile/sg/parser/statements/statement.py
iotile/sg/parser/statements/streamer_statement.py
iotile/sg/parser/statements/subtract_statement.py
iotile/sg/parser/statements/trigger_statement.py
iotile/sg/parser/statements/when_block.py
iotile/sg/scripts/__init__.py
iotile/sg/scripts/iotile_sgcompile.py
iotile/sg/scripts/iotile_sgrun.py
iotile_sensorgraph-1.1.0.dist-info/LICENSE.md
iotile_sensorgraph-1.1.0.dist-info/METADATA
iotile_sensorgraph-1.1.0.dist-info/WHEEL
iotile_sensorgraph-1.1.0.dist-info/entry_points.txt
iotile_sensorgraph-1.1.0.dist-info/top_level.txt
iotile_sensorgraph-1.1.0.dist-info/RECORD
