Metadata-Version: 2.1
Name: iotile-sensorgraph
Version: 1.1.0
Summary: IOTile SensorGraph Management and Simulation Package
Home-page: https://github.com/iotile/coretools/iotilesensorgraph
Author: Arch
Author-email: info@arch-iot.com
License: LGPLv3
Keywords: iotile,arch,embedded,hardware
Platform: UNKNOWN
Classifier: Programming Language :: Python
Classifier: Development Status :: 3 - Alpha
Classifier: License :: OSI Approved :: GNU Library or Lesser General Public License (LGPL)
Classifier: Operating System :: OS Independent
Classifier: Programming Language :: Python :: 3
Classifier: Programming Language :: Python :: 3.7
Classifier: Programming Language :: Python :: 3.8
Classifier: Programming Language :: Python :: 3.9
Classifier: Topic :: Software Development :: Libraries :: Python Modules
Requires-Python: >=3.7,<4
Requires-Dist: iotile-core (>=5.2)
Requires-Dist: pyparsing (~=2.2.0)
Requires-Dist: toposort (>=1.6)
